[{"id":4,"prev_week":null,"monday":null,"tuesday":null,"wednesday":null,"thursday":null,"friday":{"id":9,"user_session":"vcg4ebb7rk5wfunt0y4iasnz58mdurvm","shift_type_name":"Late","shift_start_time":"2021-01-01T18:00:00.000Z","shift_end_time":"2021-01-01T02:00:00.000Z","break_1_start":"null","break_1_end":"null","break_2_start":"null","break_2_end":"null","break_3_start":"null","break_3_end":"null"},"saturday":null,"sunday":null,"role_type":{"id":11,"user_session":"vcg4ebb7rk5wfunt0y4iasnz58mdurvm","role_name":"Band 5","decisions_per_hour_per_stream":[{"stream_name":"Resus","stream_object_id":201,"decisions_per_hour":0},{"stream_name":"Majors","stream_object_id":199,"decisions_per_hour":0},{"stream_name":"Minors","stream_object_id":200,"decisions_per_hour":"0.5"}]},"user_session":"vcg4ebb7rk5wfunt0y4iasnz58mdurvm","resource_name":"Dr Carling","resource_type":"core"},{"id":5,"prev_week":null,"monday":null,"tuesday":{"id":7,"user_session":"vcg4ebb7rk5wfunt0y4iasnz58mdurvm","shift_type_name":"Early","shift_start_time":"2021-01-01T06:00:00.000Z","shift_end_time":"2021-01-01T16:00:00.000Z","break_1_start":"null","break_1_end":"null","break_2_start":"null","break_2_end":"null","break_3_start":"null","break_3_end":"null"},"wednesday":{"id":8,"user_session":"vcg4ebb7rk5wfunt0y4iasnz58mdurvm","shift_type_name":"Day","shift_start_time":"2021-01-01T09:00:00.000Z","shift_end_time":"2021-01-01T18:00:00.000Z","break_1_start":"null","break_1_end":"null","break_2_start":"null","break_2_end":"null","break_3_start":"null","break_3_end":"null"},"thursday":null,"friday":null,"saturday":{"id":7,"user_session":"vcg4ebb7rk5wfunt0y4iasnz58mdurvm","shift_type_name":"Early","shift_start_time":"2021-01-01T06:00:00.000Z","shift_end_time":"2021-01-01T16:00:00.000Z","break_1_start":"null","break_1_end":"null","break_2_start":"null","break_2_end":"null","break_3_start":"null","break_3_end":"null"},"sunday":null,"role_type":{"id":9,"user_session":"vcg4ebb7rk5wfunt0y4iasnz58mdurvm","role_name":"Consultant Resus","decisions_per_hour_per_stream":[{"stream_name":"Resus","stream_object_id":201,"decisions_per_hour":"1"},{"stream_name":"Majors","stream_object_id":199,"decisions_per_hour":0},{"stream_name":"Minors","stream_object_id":200,"decisions_per_hour":0}]},"user_session":"vcg4ebb7rk5wfunt0y4iasnz58mdurvm","resource_name":"Dr Jones","resource_type":"core"},{"id":6,"prev_week":null,"monday":null,"tuesday":null,"wednesday":null,"thursday":{"id":7,"user_session":"vcg4ebb7rk5wfunt0y4iasnz58mdurvm","shift_type_name":"Early","shift_start_time":"2021-01-01T06:00:00.000Z","shift_end_time":"2021-01-01T16:00:00.000Z","break_1_start":"null","break_1_end":"null","break_2_start":"null","break_2_end":"null","break_3_start":"null","break_3_end":"null"},"friday":{"id":7,"user_session":"vcg4ebb7rk5wfunt0y4iasnz58mdurvm","shift_type_name":"Early","shift_start_time":"2021-01-01T06:00:00.000Z","shift_end_time":"2021-01-01T16:00:00.000Z","break_1_start":"null","break_1_end":"null","break_2_start":"null","break_2_end":"null","break_3_start":"null","break_3_end":"null"},"saturday":{"id":7,"user_session":"vcg4ebb7rk5wfunt0y4iasnz58mdurvm","shift_type_name":"Early","shift_start_time":"2021-01-01T06:00:00.000Z","shift_end_time":"2021-01-01T16:00:00.000Z","break_1_start":"null","break_1_end":"null","break_2_start":"null","break_2_end":"null","break_3_start":"null","break_3_end":"null"},"sunday":{"id":7,"user_session":"vcg4ebb7rk5wfunt0y4iasnz58mdurvm","shift_type_name":"Early","shift_start_time":"2021-01-01T06:00:00.000Z","shift_end_time":"2021-01-01T16:00:00.000Z","break_1_start":"null","break_1_end":"null","break_2_start":"null","break_2_end":"null","break_3_start":"null","break_3_end":"null"},"role_type":{"id":11,"user_session":"vcg4ebb7rk5wfunt0y4iasnz58mdurvm","role_name":"Band 5","decisions_per_hour_per_stream":[{"stream_name":"Resus","stream_object_id":201,"decisions_per_hour":0},{"stream_name":"Majors","stream_object_id":199,"decisions_per_hour":0},{"stream_name":"Minors","stream_object_id":200,"decisions_per_hour":"0.5"}]},"user_session":"vcg4ebb7rk5wfunt0y4iasnz58mdurvm","resource_name":"Dr Beatty","resource_type":"core"},{"id":7,"prev_week":null,"monday":null,"tuesday":null,"wednesday":null,"thursday":{"id":9,"user_session":"vcg4ebb7rk5wfunt0y4iasnz58mdurvm","shift_type_name":"Late","shift_start_time":"2021-01-01T18:00:00.000Z","shift_end_time":"2021-01-01T02:00:00.000Z","break_1_start":"null","break_1_end":"null","break_2_start":"null","break_2_end":"null","break_3_start":"null","break_3_end":"null"},"friday":{"id":10,"user_session":"vcg4ebb7rk5wfunt0y4iasnz58mdurvm","shift_type_name":"Overnight","shift_start_time":"2021-01-01T22:30:00.000Z","shift_end_time":"2021-01-01T06:30:00.000Z","break_1_start":"null","break_1_end":"null","break_2_start":"null","break_2_end":"null","break_3_start":"null","break_3_end":"null"},"saturday":null,"sunday":null,"role_type":{"id":9,"user_session":"vcg4ebb7rk5wfunt0y4iasnz58mdurvm","role_name":"Consultant Resus","decisions_per_hour_per_stream":[{"stream_name":"Resus","stream_object_id":201,"decisions_per_hour":"1"},{"stream_name":"Majors","stream_object_id":199,"decisions_per_hour":0},{"stream_name":"Minors","stream_object_id":200,"decisions_per_hour":0}]},"user_session":"vcg4ebb7rk5wfunt0y4iasnz58mdurvm","resource_name":"Dr Tyler","resource_type":"core"},{"id":9,"prev_week":null,"monday":{"id":9,"user_session":"vcg4ebb7rk5wfunt0y4iasnz58mdurvm","shift_type_name":"Late","shift_start_time":"2021-01-01T18:00:00.000Z","shift_end_time":"2021-01-01T02:00:00.000Z","break_1_start":"null","break_1_end":"null","break_2_start":"null","break_2_end":"null","break_3_start":"null","break_3_end":"null"},"tuesday":null,"wednesday":null,"thursday":null,"friday":null,"saturday":null,"sunday":null,"role_type":{"id":10,"user_session":"vcg4ebb7rk5wfunt0y4iasnz58mdurvm","role_name":"FY2 Minors","decisions_per_hour_per_stream":[{"stream_name":"Resus","stream_object_id":201,"decisions_per_hour":0},{"stream_name":"Majors","stream_object_id":199,"decisions_per_hour":0},{"stream_name":"Minors","stream_object_id":200,"decisions_per_hour":"1"}]},"user_session":"vcg4ebb7rk5wfunt0y4iasnz58mdurvm","resource_name":"Mr Monday","resource_type":"core"},{"id":10,"prev_week":null,"monday":{"id":8,"user_session":"vcg4ebb7rk5wfunt0y4iasnz58mdurvm","shift_type_name":"Day","shift_start_time":"2021-01-01T09:00:00.000Z","shift_end_time":"2021-01-01T18:00:00.000Z","break_1_start":"null","break_1_end":"null","break_2_start":"null","break_2_end":"null","break_3_start":"null","break_3_end":"null"},"tuesday":null,"wednesday":null,"thursday":null,"friday":null,"saturday":null,"sunday":null,"role_type":{"id":10,"user_session":"vcg4ebb7rk5wfunt0y4iasnz58mdurvm","role_name":"FY2 Minors","decisions_per_hour_per_stream":[{"stream_name":"Resus","stream_object_id":201,"decisions_per_hour":0},{"stream_name":"Majors","stream_object_id":199,"decisions_per_hour":0},{"stream_name":"Minors","stream_object_id":200,"decisions_per_hour":"1"}]},"user_session":"vcg4ebb7rk5wfunt0y4iasnz58mdurvm","resource_name":"Herr Montag","resource_type":"ad hoc"},{"id":11,"prev_week":{"id":10,"user_session":"vcg4ebb7rk5wfunt0y4iasnz58mdurvm","shift_type_name":"Overnight","shift_start_time":"2021-01-01T22:30:00.000Z","shift_end_time":"2021-01-01T06:30:00.000Z","break_1_start":"null","break_1_end":"null","break_2_start":"null","break_2_end":"null","break_3_start":"null","break_3_end":"null"},"monday":null,"tuesday":null,"wednesday":null,"thursday":null,"friday":null,"saturday":null,"sunday":{"id":10,"user_session":"vcg4ebb7rk5wfunt0y4iasnz58mdurvm","shift_type_name":"Overnight","shift_start_time":"2021-01-01T22:30:00.000Z","shift_end_time":"2021-01-01T06:30:00.000Z","break_1_start":"null","break_1_end":"null","break_2_start":"null","break_2_end":"null","break_3_start":"null","break_3_end":"null"},"role_type":{"id":9,"user_session":"vcg4ebb7rk5wfunt0y4iasnz58mdurvm","role_name":"Consultant Resus","decisions_per_hour_per_stream":[{"stream_name":"Resus","stream_object_id":201,"decisions_per_hour":"1"},{"stream_name":"Majors","stream_object_id":199,"decisions_per_hour":0},{"stream_name":"Minors","stream_object_id":200,"decisions_per_hour":0}]},"user_session":"vcg4ebb7rk5wfunt0y4iasnz58mdurvm","resource_name":"Monsieur Dimanche","resource_type":"ad hoc"}]